phbs/__init__.py
phbs/computational_EF.py
phbs/jakezhao.py
jakezhao-0.0.1.dist-info/LICENSE.md
jakezhao-0.0.1.dist-info/METADATA
jakezhao-0.0.1.dist-info/WHEEL
jakezhao-0.0.1.dist-info/top_level.txt
jakezhao-0.0.1.dist-info/RECORD
